pysmime/__init__.py
pysmime/core.py
pysmime/file.py
pysmime/mail.py
pysmime/pkcs11.py
pysmime/util.py
pysmime3-0.2.1.dist-info/METADATA
pysmime3-0.2.1.dist-info/RECORD
pysmime3-0.2.1.dist-info/WHEEL
pysmime3-0.2.1.dist-info/top_level.txt
