Metadata-Version: 2.1
Name: pysmime3
Version: 0.2.1
Summary: High level library for S/MIME basic functions
Home-page: http://libersoft.github.com/pysmime
Author: Lorenzo Gaggini
Author-email: lg@lgaggini.net
License: LICENSE
Keywords: smime,openssl,m2crypto
Platform: UNKNOWN
Classifier: Programming Language :: Python
Classifier: Development Status :: 4 - Beta
Classifier: Environment :: Other Environment
Classifier: Intended Audience :: Developers
Classifier: License :: OSI Approved :: GNU General Public License v3 (GPLv3)
Classifier: Operating System :: OS Independent
Classifier: Topic :: Software Development :: Libraries :: Python Modules
Classifier: Topic :: Security :: Cryptography
Requires-Dist: M2Crypto (<1.0,>=0.21.1)
Requires-Dist: psutil
